ContributionPolicy.txt
LICENSE.txt
MANIFEST.in
README.rst
requirements.txt
requirements_dev.txt
setup.cfg
setup.py
facts/__init__.py
facts/cloto_db_client.py
facts/config.py
facts/constants.py
facts/jsoncheck.py
facts/mylist.py
facts/myredis.py
facts/queue.py
facts/server.py
facts_conf/__init__.py
facts_conf/fiware-facts.cfg
fiware_facts.egg-info/PKG-INFO
fiware_facts.egg-info/SOURCES.txt
fiware_facts.egg-info/dependency_links.txt
fiware_facts.egg-info/requires.txt
fiware_facts.egg-info/top_level.txt
licenses/flask.txt
licenses/gevent.txt
licenses/pika.txt
licenses/redis-py.txt