Metadata-Version: 1.1
Name: fiware-facts
Version: 2.8.0
Summary: Server to process the incoming facts from the Orion Context Broker
Home-page: https://github.com/telefonicaid/fiware-facts
Author: Fernando Lopez Aguilar, Guillermo Jimenez Prieto
Author-email: fernando.lopezaguilar@telefonica.com, e.fiware.tid@telefonica.com
License: Apache 2.0
Download-URL: https://github.com/telefonicaid/fiware-facts/tarball/v2.8.0
Keywords: fiware,policy,manager,cloud
Platform: UNKNOWN
Classifier: License :: OSI Approved :: Apache Software License
